partition/__init__.py
partition/argument.py
partition/dp.py
partition/greedy.py
partition/kk.py
partition/partition.py
partition-0.1.2.dist-info/METADATA
partition-0.1.2.dist-info/WHEEL
partition-0.1.2.dist-info/entry_points.txt
partition-0.1.2.dist-info/top_level.txt
partition-0.1.2.dist-info/RECORD
